dart_app/__init__.py
dart_app/main.py
dart_app/config/__init__.py
dart_app/config/key_manager.py
dart_app/config/logging_config.py
dart_app/config/models.py
dart_app/gui/__init__.py
dart_app/gui/login_window.py
dart_app/gui/main_window.py
dart_app/gui/setup_window.py
dart_app/networking/__init__.py
dart_app/networking/query_retrieve_scu.py
dart_app/networking/store_scp.py
dart_app/styles/dark_theme.py
dart_app-0.1.1.dist-info/LICENSE
dart_app-0.1.1.dist-info/METADATA
dart_app-0.1.1.dist-info/WHEEL
dart_app-0.1.1.dist-info/entry_points.txt
dart_app-0.1.1.dist-info/top_level.txt
dart_app-0.1.1.dist-info/RECORD
