Metadata-Version: 2.1
Name: dart-app
Version: 0.1.1
Author-email: Yasin Abdulkadir <YasinAAbdulkadir@gmail.com>
License: LGPL-3.0-only
Requires-Python: >=3.7
License-File: LICENSE
Requires-Dist: cryptography
Requires-Dist: pydicom
Requires-Dist: pynetdicom
Requires-Dist: PySide6
Requires-Dist: SimpleITK
